{
	"_meta": {
		"internalCopies": [
			"item"
		]
	},
	"item":[
	{
		"name": "Greatsword",
		"source": "PHB",
		"page": 149,
		"srd": true,
		"basicRules": true,
		"type": "M",
		"rarity": "none",
		"weight": 6,
		"value": 5000,
		"weaponCategory": "martial",
		"property": [
			"H",
			"2H"
		],
		"dmg1": "2d6",
		"dmgType": "S",
		"sword": true,
		"weapon": true,
		"entries": []
	},
	{
		"name": "Hooked Shortspear",
		"source": "OotA",
		"page": 224,
		"type": "M",
		"rarity": "unknown",
		"weight": 2,
		"weaponCategory": "martial",
		"property": [
			"L"
		],
		"dmg1": "1d4",
		"dmgType": "P",
		"weapon": true,
		"entries": [
			"On a hit with this weapon, the wielder can forgo dealing damage and attempt to trip the target, in which case the target must succeed on a Strength saving throw or fall {@condition prone}. The DC is 8 + the wielder's Strength modifier + the wielder's proficiency bonus."
		]
	},
	{
		"name": "Maul",
		"source": "PHB",
		"page": 149,
		"srd": true,
		"basicRules": true,
		"type": "M",
		"rarity": "none",
		"weight": 10,
		"value": 1000,
		"weaponCategory": "martial",
		"property": [
			"H",
			"2H"
		],
		"dmg1": "2d6",
		"dmgType": "B",
		"hammer": true,
		"weapon": true,
		"entries": []
	},
	{
		"name": "Greataxe",
		"source": "PHB",
		"page": 149,
		"srd": true,
		"basicRules": true,
		"type": "M",
		"rarity": "none",
		"weight": 7,
		"value": 3000,
		"weaponCategory": "martial",
		"property": [
			"H",
			"2H"
		],
		"dmg1": "1d12",
		"dmgType": "S",
		"axe": true,
		"weapon": true,
		"entries": []
	},
	{
		"name": "Scimitar",
		"source": "PHB",
		"page": 149,
		"srd": true,
		"basicRules": true,
		"type": "M",
		"rarity": "none",
		"weight": 3,
		"value": 2500,
		"weaponCategory": "martial",
		"property": [
			"F",
			"L"
		],
		"dmg1": "1d6",
		"dmgType": "S",
		"sword": true,
		"weapon": true,
		"entries": []
	},
	{
		"name": "Whetstone",
		"source": "PHB",
		"page": 150,
		"srd": true,
		"basicRules": true,
		"type": "G",
		"rarity": "none",
		"weight": 1,
		"value": 1,
		"entries": []
	},
	{
		"name": "Oil (flask)",
		"source": "PHB",
		"page": 152,
		"srd": true,
		"basicRules": true,
		"type": "G",
		"rarity": "none",
		"weight": 1,
		"value": 10,
		"entries": [
			"Oil usually comes in a clay flask that holds 1 pint. As an action, you can splash the oil in this flask onto a creature within 5 feet of you or throw it up to 20 feet, shattering it on impact. Make a ranged attack against a target creature or object, treating the oil as an improvised weapon. On a hit, the target is covered in oil. If the target takes any fire damage before the oil dries (after 1 minute), the target takes an additional 5 fire damage from the burning oil. You can also pour a flask of oil on the ground to cover a 5-foot-square area, provided that the surface is level. If lit, the oil burns for 2 rounds and deals 5 fire damage to any creature that enters the area or ends its turn in the area. A creature can take this damage only once per turn."
		]
	},
	{
		"name": "Ale (Gallon)",
		"source": "PHB",
		"page": 158,
		"srd": true,
		"basicRules": true,
		"type": "FD",
		"rarity": "none",
		"value": 20,
		"entries": []
	},
	{
		"name": "Waterskin",
		"source": "PHB",
		"page": 153,
		"srd": true,
		"basicRules": true,
		"type": "G",
		"rarity": "none",
		"weight": 5,
		"weightNote": "(full)",
		"value": 20,
		"entries": [
			"A waterskin can hold up to 4 pints of liquid."
		]
	},
	{
		"name": "Chunk of Meat",
		"source": "PHB",
		"page": 158,
		"srd": true,
		"basicRules": true,
		"type": "FD",
		"rarity": "none",
		"value": 30,
		"entries": []
	},
	{
		"name": "Sack",
		"source": "PHB",
		"page": 153,
		"srd": true,
		"basicRules": true,
		"type": "G",
		"rarity": "none",
		"weight": 0.5,
		"value": 1,
		"entries": [
			"A sack can hold up to 1 cubic foot or 30 pounds of gear."
		],
		"containerCapacity": {
			"weight": [
				30
			]
		}
	},
	{
		"name": "Grappling Hook",
		"source": "PHB",
		"page": 150,
		"srd": true,
		"basicRules": true,
		"type": "G",
		"rarity": "none",
		"weight": 4,
		"value": 200,
		"entries": []
	},
	{
		"name": "Barrel",
		"source": "PHB",
		"page": 153,
		"srd": true,
		"basicRules": true,
		"type": "G",
		"rarity": "none",
		"weight": 70,
		"value": 200,
		"entries": [
			"A barrel can hold 40 gallons of liquid or 4 cubic feet of solids."
		]
	},
	{
		"name": "Crowbar",
		"source": "PHB",
		"page": 151,
		"srd": true,
		"basicRules": true,
		"type": "G",
		"rarity": "none",
		"weight": 5,
		"value": 200,
		"entries": [
			"Using a crowbar grants advantage to Strength checks where the crowbar's leverage can be applied."
		]
	},
	{
		"name": "Manacles",
		"source": "PHB",
		"page": 152,
		"srd": true,
		"basicRules": true,
		"type": "G",
		"rarity": "none",
		"weight": 6,
		"value": 200,
		"entries": [
			"These metal restraints can bind a Small or Medium creature. Escaping the manacles requires a successful DC 20 Dexterity check. Breaking them requires a successful DC 20 Strength check. Each set of manacles comes with one key. Without the key, a creature proficient with {@item thieves' tools|PHB} can pick the manacles' lock with a successful DC 15 Dexterity check. Manacles have 15 hit points."
		]
	},
	{
		"name": "Sheep",
		"source": "PHB",
		"page": 157,
		"srd": true,
		"basicRules": true,
		"type": "TG",
		"rarity": "none",
		"value": 200,
		"entries": []
	},
	{
		"name": "Portable Ram",
		"source": "PHB",
		"page": 153,
		"srd": true,
		"basicRules": true,
		"type": "G",
		"rarity": "none",
		"weight": 35,
		"value": 400,
		"entries": [
			"You can use a portable ram to break down doors. When doing so, you gain a +4 bonus on the Strength check. One other character can help you use the ram, giving you advantage on this check."
		]
	},
	{
		"name": "Horn",
		"source": "PHB",
		"page": 154,
		"srd": true,
		"basicRules": true,
		"type": "INS",
		"rarity": "none",
		"weight": 2,
		"value": 300,
		"entries": [],
		"additionalSources": [
			{
				"source": "XGE",
				"page": 83
			}
		]
	},
	{
		"name": "Saddlebags",
		"source": "PHB",
		"page": 157,
		"srd": true,
		"basicRules": true,
		"type": "TAH",
		"rarity": "none",
		"weight": 8,
		"value": 400,
		"entries": []
	},
	{
		"name": "Healer's Kit",
		"source": "PHB",
		"page": 151,
		"srd": true,
		"basicRules": true,
		"type": "G",
		"rarity": "none",
		"weight": 3,
		"value": 500,
		"entries": [
			"This kit is a leather pouch containing bandages, salves, and splints. The kit has ten uses. As an action, you can expend one use of the kit to stabilize a creature that has 0 hit points, without needing to make a Wisdom ({@skill Medicine}) check."
		],
		"hasFluffImages": true
	},
	{
		"name": "Hunting Trap",
		"source": "PHB",
		"page": 152,
		"srd": true,
		"basicRules": true,
		"type": "G",
		"rarity": "none",
		"weight": 25,
		"value": 500,
		"entries": [
			"When you use your action to set it, this trap forms a saw-toothed steel ring that snaps shut when a creature steps on a pressure plate in the center. The trap is affixed by a heavy chain to an immobile object, such as a tree or a spike driven into the ground. A creature that steps on the plate must succeed on a DC 13 Dexterity saving throw or take {@damage 1d4} piercing damage and stop moving. Thereafter, until the creature breaks free of the trap, its movement is limited by the length of the chain (typically 3 feet long). A creature can use its action to make a DC 13 Strength check, freeing itself or another creature within its reach on a success. Each failed check deals 1 piercing damage to the trapped creature."
		]
	},
	{
		"name": "Pack Saddle",
		"source": "PHB",
		"page": 157,
		"srd": true,
		"basicRules": true,
		"type": "TAH",
		"rarity": "none",
		"weight": 15,
		"value": 500,
		"entries": []
	},
	{
		"name": "Scale Mail",
		"source": "PHB",
		"page": 144,
		"srd": true,
		"basicRules": true,
		"type": "MA",
		"rarity": "none",
		"weight": 45,
		"value": 5000,
		"ac": 14,
		"armor": true,
		"stealth": true,
		"entries": [
			"This armor consists of a coat and leggings (and perhaps a separate skirt) of leather covered with overlapping pieces of metal, much like the scales of a fish. The suit includes gauntlets."
		]
	},
	{
		"name": "Monster Hunter's Pack",
		"source": "VRGR",
		"page": 34,
		"otherSources": [
			{
				"source": "CoS",
				"page": 209
			}
		],
		"type": "G",
		"rarity": "none",
		"weight": 48.5,
		"value": 3300,
		"entries": [
			"Includes:",
			{
				"type": "list",
				"items": [
					"a {@item chest|phb}",
					"a {@item crowbar|phb}",
					"a {@item hammer|phb}",
					"three wooden stakes",
					"a {@item holy symbol|phb}",
					"a {@item holy water (flask)|phb|flask of holy water}",
					"a set of {@item manacles|phb}",
					"a {@item steel mirror|phb}",
					"a {@item oil (flask)|phb|flask of oil}",
					"a {@item tinderbox|phb}",
					"3 {@item torch|phb|torches}"
				]
			}
		],
		"packContents": [
			"backpack|phb",
			"chest|phb",
			"crowbar|phb",
			"hammer|phb",
			{
				"special": "wooden stake",
				"quantity": 3
			},
			"holy symbol|phb",
			"holy water (flask)|phb",
			"manacles|phb",
			"steel mirror|phb",
			"oil (flask)|phb",
			"tinderbox|phb",
			{
				"item": "torch|phb",
				"quantity": 3
			}
		]
	}
]
}
